pyapksigner
