Metadata-Version: 2.1
Name: pyapksigner
Version: 0.0.4
Summary: Sign the apk file
Home-page: https://github.com/ksg97031/pyapksigner
Author: ksg97031
Author-email: ksg97031@gmail.com
License: UNKNOWN
Platform: UNKNOWN
Classifier: Programming Language :: Python :: 3
Classifier: License :: OSI Approved :: MIT License
Classifier: Operating System :: OS Independent
Requires-Python: >=3.8
